{
  "volunteers": [
    {
      "id": "5e2f5ca8-58e2-48b0-9537-72a9d5bf11c8",
      "firstName": "Chris",
      "lastName": "Low",
      "phone": ""
    },
    {
      "id": "44296024-8414-4503-b603-e46ae483b216",
      "firstName": "Esther",
      "lastName": "Wong",
      "phone": ""
    },
    {
      "id": "3cf59c18-8267-4642-985e-9930a5479bf9",
      "firstName": "Michael",
      "lastName": "Tan",
      "phone": ""
    },
    {
      "id": "501b53fd-e055-4c2c-8a51-0bac95cbbd1f",
      "firstName": "Gary",
      "lastName": "Mok",
      "phone": ""
    },
    {
      "id": "45ccc7b1-4208-4b8d-b287-74005560c816",
      "firstName": "Eric",
      "lastName": "Tan",
      "phone": ""
    },
    {
      "id": "b3c7bc7b-5262-4aa4-9bec-cdd5da0cd34f",
      "firstName": "Grace",
      "lastName": "Ng",
      "phone": ""
    }
  ]
}